edapipeline/__init__.py
edapipeline/__version__.py
edapipeline/core.py
edapipeline/utils.py
edapipeline-0.1.4.dist-info/licenses/LICENSE
edapipeline-0.1.4.dist-info/METADATA
edapipeline-0.1.4.dist-info/WHEEL
edapipeline-0.1.4.dist-info/top_level.txt
edapipeline-0.1.4.dist-info/RECORD
