Metadata-Version: 2.4
Name: edapipeline
Version: 0.1.4
Summary: Comprehensive Exploratory Data Analysis Pipeline
Author-email: Syed Nazmus Sakib <your.email@example.com>
License: MIT
Project-URL: Homepage, https://github.com/SyedNazmusSakib-SNS/EDAPipeline
Project-URL: Bug Tracker, https://github.com/SyedNazmusSakib-SNS/EDAPipeline/issues
Classifier: Programming Language :: Python :: 3
Classifier: Programming Language :: Python :: 3.7
Classifier: Programming Language :: Python :: 3.8
Classifier: Programming Language :: Python :: 3.9
Classifier: Programming Language :: Python :: 3.10
Classifier: Programming Language :: Python :: 3.11
Classifier: Programming Language :: Python :: 3.12
Classifier: License :: OSI Approved :: MIT License
Classifier: Operating System :: OS Independent
Classifier: Topic :: Scientific/Engineering :: Information Analysis
Classifier: Topic :: Scientific/Engineering :: Visualization
Requires-Python: >=3.7
License-File: LICENSE
Requires-Dist: numpy>=1.19.0
Requires-Dist: pandas>=1.1.0
Requires-Dist: matplotlib>=3.3.0
Requires-Dist: seaborn>=0.11.0
Requires-Dist: scipy>=1.5.0
Dynamic: license-file
